client/SignatureDataset.py
client/__init__.py
client/augment.py
client/batch_process.py
client/gridlines.py
client/metrics.py
client/segment.py
versign/VerSign.py
versign/__init__.py
versign/metrics/__init__.py
versign/metrics/metrics.py
versign/train_test/Classifier.py
versign/train_test/FeatureExtractor.py
versign/train_test/SignatureDataset.py
versign/train_test/__init__.py
versign/utils/__init__.py
versign/utils/augment.py
versign/utils/batch_process.py
versign/utils/gridlines.py
versign/utils/segment.py
versign-0.0.2.dist-info/LICENSE
versign-0.0.2.dist-info/METADATA
versign-0.0.2.dist-info/WHEEL
versign-0.0.2.dist-info/top_level.txt
versign-0.0.2.dist-info/RECORD
