Metadata-Version: 2.1
Name: versign
Version: 0.0.2
Summary: Signature verification package for verifying offline signatures using writer-independent features.
Home-page: https://github.com/saifkhichi96/versign-core
Author: Saif Khan
Author-email: saifkhichi96@gmail.com
License: UNKNOWN
Platform: UNKNOWN
Classifier: Programming Language :: Python :: 3
Classifier: License :: OSI Approved :: MIT License
Classifier: Operating System :: OS Independent
Requires-Python: >=3
Requires-Dist: joblib
Requires-Dist: numpy (>=1.10.4)
Requires-Dist: opencv-contrib-python
Requires-Dist: Pillow
Requires-Dist: scikit-image
Requires-Dist: scikit-learn (>=0.19.0)
Requires-Dist: scipy
Requires-Dist: torch (>=1.0)
Requires-Dist: torchvision (>=0.2.1)
